{
  "batch_id": "batch_0012",
  "paper_count": 10,
  "paper_ids": [
    "paper_000111",
    "paper_000112",
    "paper_000113",
    "paper_000114",
    "paper_000115",
    "paper_000116",
    "paper_000117",
    "paper_000118",
    "paper_000119",
    "paper_000120"
  ],
  "papers": [
    {
      "paper_id": "paper_000111",
      "entry_type": "article",
      "title": "冠心病和肌少症",
      "authors": [
        "江鹏程",
        "田文",
        "孙龙凤",
        "齐国先"
      ],
      "year": 2022,
      "journal": "中国实用内科杂志",
      "doi": "10.19538/j.nk2022080107",
      "abstract": "冠心病是老年常见的慢性病,肌少症是常见的老年综合征,二者相互作用和影响,成为影响老年健康的严峻问题。肌少症的发生与冠状动脉粥样硬化的危险因素显著相关,尤其是糖尿病、高血压和血脂异常等,对老年冠心病患者生活质量及预后具有显著影响。动脉粥样硬化相关性疾病也会导致肌肉质量的急慢性丧失,它们之间相互作用,在发病、预后之间存在明显关联。已有多项研究提示肌少症可作为冠心病独立的预后因素。因此,对于老年冠心病患者要进行肌少症的筛查和评估,慢性肌少症可以参考2021中国老年人肌少症诊疗专家共识,急性肌少症可以应用肌少症指数间接评估。对于老年冠心病合并肌少症患者的治疗鲜有报告,目前的治疗原则是在冠心病治疗的基础上兼顾肌少症的干预。公认的肌少症干预方法为非药物疗法,核心是生活方式的改变,包括运动训练和营养干预,这些措施同时也适用于老年冠心病患者。常用于冠心病治疗的他汀类药物和肾素血管紧张素系统(RAS)阻断剂对肌少症的影响应该给予关注,其他药物尚需进一步研究。",
      "keywords": [
        "冠心病",
        "肌少症",
        "老年",
        "动脉粥样硬化",
        "评估"
      ],
      "normalized_title": "冠心病和肌少症",
      "raw_bibtex": "@ARTICLE{10.19538/j.nk2022080107,\n\tauthor = {江鹏程 and 田文 and 孙龙凤 and 齐国先},\n\ttitle = {冠心病和肌少症},\n\tjournal = {中国实用内科杂志},\n\tyear = {2022},\n\tkeywords = {冠心病;肌少症;老年;动脉粥样硬化;评估},\n\tabstract = {冠心病是老年常见的慢性病,肌少症是常见的老年综合征,二者相互作用和影响,成为影响老年健康的严峻问题。肌少症的发生与冠状动脉粥样硬化的危险因素显著相关,尤其是糖尿病、高血压和血脂异常等,对老年冠心病患者生活质量及预后具有显著影响。动脉粥样硬化相关性疾病也会导致肌肉质量的急慢性丧失,它们之间相互作用,在发病、预后之间存在明显关联。已有多项研究提示肌少症可作为冠心病独立的预后因素。因此,对于老年冠心病患者要进行肌少症的筛查和评估,慢性肌少症可以参考2021中国老年人肌少症诊疗专家共识,急性肌少症可以应用肌少症指数间接评估。对于老年冠心病合并肌少症患者的治疗鲜有报告,目前的治疗原则是在冠心病治疗的基础上兼顾肌少症的干预。公认的肌少症干预方法为非药物疗法,核心是生活方式的改变,包括运动训练和营养干预,这些措施同时也适用于老年冠心病患者。常用于冠心病治疗的他汀类药物和肾素血管紧张素系统(RAS)阻断剂对肌少症的影响应该给予关注,其他药物尚需进一步研究。},\n\tdoi = {10.19538/j.nk2022080107},\n\turl = {https://link.cnki.net/doi/10.19538/j.nk2022080107},\n\tvolume = {42},\n\tnumber = {08},\n\tpages = {638-642},\n\tissn = {1005-2194},\n\tnote = {CNKI}\n}",
      "source_files": [
        "CNKI-20260403233112547.enw"
      ],
      "source_keys": [
        "10.19538/j.nk2022080107"
      ],
      "merged_from": [],
      "status": "unprocessed"
    },
    {
      "paper_id": "paper_000112",
      "entry_type": "article",
      "title": "基于2050年中国人口发展愿景的工程科技需求分析",
      "authors": [
        "马茹",
        "王宏伟",
        "张静"
      ],
      "year": 2022,
      "journal": "技术经济",
      "doi": null,
      "abstract": "“人口”是影响未来趋势的核心驱动力之一。本文面向2050年人口发展愿景开展工程科技需求分析。研究发现:2050年,中国人口总量进入负增长,实现适度生育面临较大压力,老龄化程度持续加深,劳动年龄人口规模及比重下降,人口健康水平与素质能力稳步提升,人口向核心城市群集聚更趋明显。人口老龄化对老年慢性病诊治及管理、老年人日常性照护需求增加,劳动力结构性短缺亟需填补数量、增强身心健康,人口健康水平提升使对治愈重大疾病和罕见病、替换故障组织及器官需求增多,人口综合素质提高推动健康意识从被动医疗向主动健康转变、追求多样化个性化品质化医疗服务等。对此,要瞄准精准医疗、智慧医疗、远程医疗、生物打印、人工智能、大数据等工程科技手段。",
      "keywords": [
        "2050年",
        "愿景",
        "需求",
        "人口",
        "工程科技"
      ],
      "normalized_title": "基于2050年中国人口发展愿景的工程科技需求分析",
      "raw_bibtex": "@ARTICLE{endnote_000113,\n\tauthor = {马茹 and 王宏伟 and 张静},\n\ttitle = {基于2050年中国人口发展愿景的工程科技需求分析},\n\tjournal = {技术经济},\n\tyear = {2022},\n\tkeywords = {2050年;愿景;需求;人口;工程科技},\n\tabstract = {“人口”是影响未来趋势的核心驱动力之一。本文面向2050年人口发展愿景开展工程科技需求分析。研究发现:2050年,中国人口总量进入负增长,实现适度生育面临较大压力,老龄化程度持续加深,劳动年龄人口规模及比重下降,人口健康水平与素质能力稳步提升,人口向核心城市群集聚更趋明显。人口老龄化对老年慢性病诊治及管理、老年人日常性照护需求增加,劳动力结构性短缺亟需填补数量、增强身心健康,人口健康水平提升使对治愈重大疾病和罕见病、替换故障组织及器官需求增多,人口综合素质提高推动健康意识从被动医疗向主动健康转变、追求多样化个性化品质化医疗服务等。对此,要瞄准精准医疗、智慧医疗、远程医疗、生物打印、人工智能、大数据等工程科技手段。},\n\turl = {https://kns.cnki.net/kcms2/article/abstract?v=Vs3rztogjcVBSWhmnPKiYVoZCkZO1s-NNQYAV-vmIZT48NQpUuM3xipn2MuzBFT1EiP2rgpGu8y8jQY1vDMTcCLYshYTyVhFbZHc4vg1pO6uAVFtxMtg8H4ZZF3U6fFiuo4ZNl4AD5N6Kj3foDeF_q30BsnyuqfrOTBlUGamsJ3-nSMv136JzEmhhTkgXR1e&uniplatform=NZKPT&language=CHS},\n\tvolume = {41},\n\tnumber = {07},\n\tpages = {73-82},\n\tissn = {1002-980X},\n\tnote = {CNKI}\n}",
      "source_files": [
        "CNKI-20260403233112547.enw"
      ],
      "source_keys": [
        "endnote_000113"
      ],
      "merged_from": [],
      "status": "unprocessed"
    },
    {
      "paper_id": "paper_000113",
      "entry_type": "article",
      "title": "2022年《中华护理教育》专题策划",
      "authors": [],
      "year": 2022,
      "journal": "中华护理教育",
      "doi": null,
      "abstract": "<正>一、健康中国建设与护理教育:1.中国护理模式与理论研究2.专科(方向)护理人才培养:老年、中医、助产、安宁疗护、慢性病、公共卫生3.专科护士使用、评价和再培养4.健康/护理科普二、护理教育改革与发展:1.二级学科设立与发展2.跨学科、跨专业人才培养3.硕士/博士研究生培养及导师队伍建设4.以评促改:专业认证、学科评估5.以赛促教:医学生(护理专业)技能技术大赛6.课程改革:金课、课程思政、信息化和智能化技术应用7.教育评价改革:学生评价改革、教师评价改革8.护理临床教师队伍建设9.能力培养:临床思维能力培养、创新能力培养",
      "keywords": [],
      "normalized_title": "2022年 中华护理教育 专题策划",
      "raw_bibtex": "@ARTICLE{endnote_000129,\n\ttitle = {2022年《中华护理教育》专题策划},\n\tjournal = {中华护理教育},\n\tyear = {2021},\n\tabstract = {<正>一、健康中国建设与护理教育:1.中国护理模式与理论研究2.专科(方向)护理人才培养:老年、中医、助产、安宁疗护、慢性病、公共卫生3.专科护士使用、评价和再培养4.健康/护理科普二、护理教育改革与发展:1.二级学科设立与发展2.跨学科、跨专业人才培养3.硕士/博士研究生培养及导师队伍建设4.以评促改:专业认证、学科评估5.以赛促教:医学生(护理专业)技能技术大赛6.课程改革:金课、课程思政、信息化和智能化技术应用7.教育评价改革:学生评价改革、教师评价改革8.护理临床教师队伍建设9.能力培养:临床思维能力培养、创新能力培养},\n\turl = {https://kns.cnki.net/kcms2/article/abstract?v=Vs3rztogjcVT_ktyTfxjSNdTix88Vl1JPtGGXw-oQqd-Bwi6f9gxH7XueJJDDBQE0rbdtD9FVk4AKvdm3Zo4xBwE6uqLwHcoqov61TzKTSknzsEx9n-VvrYEABAPROmV81iCObHtc-pU2_b9n7zgSjB2xl_XmKaBuimNxTQROkQZsN98HKydfvtA14HJV3cK&uniplatform=NZKPT&language=CHS},\n\tvolume = {18},\n\tnumber = {12},\n\tpages = {1058},\n\tissn = {1672-9234},\n\tnote = {CNKI}\n}",
      "source_files": [
        "CNKI-20260403233112547.enw"
      ],
      "source_keys": [
        "endnote_000114",
        "endnote_000127",
        "endnote_000129"
      ],
      "merged_from": [
        "raw_000127",
        "raw_000129"
      ],
      "status": "unprocessed"
    },
    {
      "paper_id": "paper_000114",
      "entry_type": "article",
      "title": "上海市嘉定区社区老年人的失能现状及其影响因素",
      "authors": [
        "张妍",
        "袁红",
        "金亚清",
        "于宏杰"
      ],
      "year": 2022,
      "journal": "中华疾病控制杂志",
      "doi": "10.16462/j.cnki.zhjbkz.2022.07.007",
      "abstract": "目的 了解上海市嘉定区老年人的失能现状并分析其影响因素,为老年人失能防控和健康老龄化建设提供科学依据。方法 采用多阶段随机抽样方法,选取≥60岁的嘉定区户籍老年人群作为调查对象,采用世界卫生组织研发的自报健康调查量表测量老年人失能情况;应用多因素Logistic回归分析模型及列线图分析老年人失能的影响因素。结果 共调查老年人4 773人,其中失能老人495人,失能率为11.4%,女性的失能率(13.6%)高于男性(8.9%)。老年人自我评价在认知记忆、视力辨认、疼痛不适、睡眠及活动行走这五方面存在更多的失能,失能率分别为31.7%、23.0%、21.6%、20.4%和13.6%。多因素分析结果显示,年龄大、自评健康较差、患2种及以上慢性病的老年人失能率较高(均有P<0.05);每周体育锻炼、饮酒的老年人失能率较低(均有P<0.05)。结论 嘉定区社区老年人失能率较高。应加强慢性病管理,关注老年人的不同照护需求,开展针对性的早期预防和干预。",
      "keywords": [
        "失能",
        "老年人",
        "影响因素",
        "列线图"
      ],
      "normalized_title": "上海市嘉定区社区老年人的失能现状及其影响因素",
      "raw_bibtex": "@ARTICLE{10.16462/j.cnki.zhjbkz.2022.07.007,\n\tauthor = {张妍 and 袁红 and 金亚清 and 于宏杰},\n\ttitle = {上海市嘉定区社区老年人的失能现状及其影响因素},\n\tjournal = {中华疾病控制杂志},\n\tyear = {2022},\n\tkeywords = {失能;老年人;影响因素;列线图},\n\tabstract = {目的 了解上海市嘉定区老年人的失能现状并分析其影响因素,为老年人失能防控和健康老龄化建设提供科学依据。方法 采用多阶段随机抽样方法,选取≥60岁的嘉定区户籍老年人群作为调查对象,采用世界卫生组织研发的自报健康调查量表测量老年人失能情况;应用多因素Logistic回归分析模型及列线图分析老年人失能的影响因素。结果 共调查老年人4 773人,其中失能老人495人,失能率为11.4%,女性的失能率(13.6%)高于男性(8.9%)。老年人自我评价在认知记忆、视力辨认、疼痛不适、睡眠及活动行走这五方面存在更多的失能,失能率分别为31.7%、23.0%、21.6%、20.4%和13.6%。多因素分析结果显示,年龄大、自评健康较差、患2种及以上慢性病的老年人失能率较高(均有P<0.05);每周体育锻炼、饮酒的老年人失能率较低(均有P<0.05)。结论 嘉定区社区老年人失能率较高。应加强慢性病管理,关注老年人的不同照护需求,开展针对性的早期预防和干预。},\n\tdoi = {10.16462/j.cnki.zhjbkz.2022.07.007},\n\turl = {https://link.cnki.net/doi/10.16462/j.cnki.zhjbkz.2022.07.007},\n\tvolume = {26},\n\tnumber = {07},\n\tpages = {784-789},\n\tissn = {1674-3679},\n\tnote = {CNKI}\n}",
      "source_files": [
        "CNKI-20260403233112547.enw"
      ],
      "source_keys": [
        "10.16462/j.cnki.zhjbkz.2022.07.007"
      ],
      "merged_from": [],
      "status": "unprocessed"
    },
    {
      "paper_id": "paper_000115",
      "entry_type": "article",
      "title": "老年慢性病患者移动医疗照护体验的Meta整合",
      "authors": [
        "熊佳铭",
        "余红雨",
        "苏瑾",
        "赵倬睿",
        "杨巧红"
      ],
      "year": 2022,
      "journal": "中华护理杂志",
      "doi": null,
      "abstract": "目的 系统评价老年慢性病患者参与移动医疗照护体验的质性研究,为提高和改善老年患者对移动医疗的可及性提供依据。方法 计算机检索PubMed、Embase、The Cochrane Library、Web of Science、Scopus、CINAHL、ProQuest、中国知网、万方数据库、维普中文生物医学期刊、中国生物医学文献数据库,检索有关老年慢性病患者对使用移动医疗的态度和体验的质性研究,检索时限从2000年1月—2022年3月。使用乔安娜布里格斯研究所质性研究评估工具评价文献质量。结果 共纳入22篇研究,提炼出92个明确的研究结果,将相似的研究结果归纳形成12个新类别,综合成3个整合结果:老年慢性病患者参与移动医疗的良好体验、老年慢性病患者参与移动医疗的不佳体验、老年慢性病患者对移动医疗的偏好和期望。结论 老年慢性病患者参与移动医疗的适应体验多样化,需要结合患者情况,从移动医疗设备、医院、社区、家庭和个人多层面完善移动医疗照护服务体系,提升老年慢性病患者使用移动医疗照护服务的可及性和体验。",
      "keywords": [
        "老年人",
        "慢性病",
        "移动医疗",
        "体验",
        "Meta整合",
        "循证护理学"
      ],
      "normalized_title": "老年慢性病患者移动医疗照护体验的meta整合",
      "raw_bibtex": "@ARTICLE{endnote_000116,\n\tauthor = {熊佳铭 and 余红雨 and 苏瑾 and 赵倬睿 and 杨巧红},\n\ttitle = {老年慢性病患者移动医疗照护体验的Meta整合},\n\tjournal = {中华护理杂志},\n\tyear = {2022},\n\tkeywords = {老年人;慢性病;移动医疗;体验;Meta整合;循证护理学},\n\tabstract = {目的 系统评价老年慢性病患者参与移动医疗照护体验的质性研究,为提高和改善老年患者对移动医疗的可及性提供依据。方法 计算机检索PubMed、Embase、The Cochrane Library、Web of Science、Scopus、CINAHL、ProQuest、中国知网、万方数据库、维普中文生物医学期刊、中国生物医学文献数据库,检索有关老年慢性病患者对使用移动医疗的态度和体验的质性研究,检索时限从2000年1月—2022年3月。使用乔安娜布里格斯研究所质性研究评估工具评价文献质量。结果 共纳入22篇研究,提炼出92个明确的研究结果,将相似的研究结果归纳形成12个新类别,综合成3个整合结果:老年慢性病患者参与移动医疗的良好体验、老年慢性病患者参与移动医疗的不佳体验、老年慢性病患者对移动医疗的偏好和期望。结论 老年慢性病患者参与移动医疗的适应体验多样化,需要结合患者情况,从移动医疗设备、医院、社区、家庭和个人多层面完善移动医疗照护服务体系,提升老年慢性病患者使用移动医疗照护服务的可及性和体验。},\n\turl = {https://kns.cnki.net/kcms2/article/abstract?v=Vs3rztogjcVVEgucFsQNKcmrpJeX9LtjZ3Is6KpupvigpfDKlFSR9B0ihLgFRBFtEnMAB3uNa7alfz8PV8-DxV3tnoCLRKu_z1I7i51VkbSi8fpD2RKhC76U2dQ6fiV9Z55MISuxhrBGPDaV3mkxPsyB7bwxyiuNNQ-jGT5bZTeBhPcDIzQ_XuQbKD-U75gp&uniplatform=NZKPT&language=CHS},\n\tvolume = {57},\n\tnumber = {13},\n\tpages = {1641-1649},\n\tissn = {0254-1769},\n\tnote = {CNKI}\n}",
      "source_files": [
        "CNKI-20260403233112547.enw"
      ],
      "source_keys": [
        "endnote_000116"
      ],
      "merged_from": [],
      "status": "unprocessed"
    },
    {
      "paper_id": "paper_000116",
      "entry_type": "article",
      "title": "基于多元统计学方法的骨量肌量减少性肥胖综合征的结构特征研究",
      "authors": [
        "聂义珍",
        "闫朝岐",
        "燕巍",
        "付红梅",
        "赵兴鹃",
        "尹慧",
        "吴群红"
      ],
      "year": 2022,
      "journal": "中国全科医学",
      "doi": null,
      "abstract": "背景 骨量肌量减少性肥胖综合征(OSO)是一种严重损害老年人健康的疾病,对疾病进行临床分型可为疾病的临床诊治提供指导。基于OSO诊断变量间的相关性对OSO进行分型,并探寻OSO的结构特征,可为OSO的防治提供新的思路。目的 探索OSO的结构特征,为实现OSO的个体化诊治提供理论依据。方法 本研究为横断面研究。于2018年1月至2020年10月,采用随机抽样法,选取在哈尔滨医科大学附属第二医院体检中心接受健康体检、年龄≥60岁的老年OSO患者作为研究对象,采集其OSO诊断变量〔四肢骨骼肌指数,握力,体脂百分比(BF%),腰椎1~4(L1~4)、髋部、股骨颈骨密度(BMD),体质指数(BMI),腰围,步速〕、社会人口学特征、生活方式、常见慢性病患病情况等方面的资料。在利用因子分析法对OSO诊断变量数据进行分析前,采用KMO检验、Bartlett's球形检验评价OSO诊断变量数据是否适合进行因子分析。通过主成分分析法,提取特征值≥1.000的成分,并运用最大方差正交旋转法得出方差最大正交旋转矩阵。根据因子正交旋转矩阵,对公因子进行命名。基于公因子得分,利用离差平方和系统聚类法生成树状结构并对患者进行分类,通过比较不同类别患者间诊断变量水平和临床特征的差异,分析OSO的结构特征。结果 共纳入107例老年OSO患者。KMO值为0.688,Bartlett's球形检验χ2=492.374,P<0.001,表明OSO诊断变量数据适合进行因子分析;按特征根>1.000的标准可提取3个公因子(骨质疏松因子、肌肉+体脂因子、肥胖因子),3个公因子的累积方差贡献率为81.408%,各诊断变量在所属公因子上的载荷值为0.770~0.918。聚类分析结果显示,共将OSO患者分为3类。不同类别人群四肢骨骼肌指数、握力、BF%、BMDL1~4、BMD髋部、BMD股骨颈、BMI、腰围比较,差异均有统计学意义(P<0.05)。其中第1类人群的BMDL1~4、BMD髋部、BMD股骨颈均低于其他两类人群(P<0.05);第2类人群的BMI和腰围均低于其他两类人群(P<0.05);第3类人群的四肢骨骼肌指数、握力和BMD均高于其他两类人群,BF%低于其他两类人群(P<0.05)。不同类别人群性别、受教育程度、个人月收入分布、总胆固醇(TC)、高密度脂蛋白胆固醇(HDL-C)、尿酸(UA)、肌酐(Cr)水平比较,差异有统计学意义(P<0.05)。第1类人群中本科以下学历者占比高于第3类人群(P<0.017);第2类人群TC水平高于第3类人群(P<0.05);第3类人群个人月收入≥5 000元者占比,以及UA、Cr水平均高于其他两类人群,女性占比低于其他两类人群(P<0.05或P<0.017)。结论 可从骨质疏松、肌肉与体脂、肥胖3个方面对OSO诊断变量进行概括和解释;OSO患者具有不同的结构特征。应用多元统计学方法研究OSO患者的结构特征,有助于实现对不同类型OSO患者的个体化管理。",
      "keywords": [
        "骨量肌量减少性肥胖综合征",
        "因子分析",
        "聚类分析",
        "多元统计学方法"
      ],
      "normalized_title": "基于多元统计学方法的骨量肌量减少性肥胖综合征的结构特征研究",
      "raw_bibtex": "@ARTICLE{endnote_000117,\n\tauthor = {聂义珍 and 闫朝岐 and 燕巍 and 付红梅 and 赵兴鹃 and 尹慧 and 吴群红},\n\ttitle = {基于多元统计学方法的骨量肌量减少性肥胖综合征的结构特征研究},\n\tjournal = {中国全科医学},\n\tyear = {2022},\n\tkeywords = {骨量肌量减少性肥胖综合征;因子分析;聚类分析;多元统计学方法},\n\tabstract = {背景 骨量肌量减少性肥胖综合征(OSO)是一种严重损害老年人健康的疾病,对疾病进行临床分型可为疾病的临床诊治提供指导。基于OSO诊断变量间的相关性对OSO进行分型,并探寻OSO的结构特征,可为OSO的防治提供新的思路。目的 探索OSO的结构特征,为实现OSO的个体化诊治提供理论依据。方法 本研究为横断面研究。于2018年1月至2020年10月,采用随机抽样法,选取在哈尔滨医科大学附属第二医院体检中心接受健康体检、年龄≥60岁的老年OSO患者作为研究对象,采集其OSO诊断变量〔四肢骨骼肌指数,握力,体脂百分比(BF%),腰椎1~4(L1~4)、髋部、股骨颈骨密度(BMD),体质指数(BMI),腰围,步速〕、社会人口学特征、生活方式、常见慢性病患病情况等方面的资料。在利用因子分析法对OSO诊断变量数据进行分析前,采用KMO检验、Bartlett's球形检验评价OSO诊断变量数据是否适合进行因子分析。通过主成分分析法,提取特征值≥1.000的成分,并运用最大方差正交旋转法得出方差最大正交旋转矩阵。根据因子正交旋转矩阵,对公因子进行命名。基于公因子得分,利用离差平方和系统聚类法生成树状结构并对患者进行分类,通过比较不同类别患者间诊断变量水平和临床特征的差异,分析OSO的结构特征。结果 共纳入107例老年OSO患者。KMO值为0.688,Bartlett's球形检验χ2=492.374,P<0.001,表明OSO诊断变量数据适合进行因子分析;按特征根>1.000的标准可提取3个公因子(骨质疏松因子、肌肉+体脂因子、肥胖因子),3个公因子的累积方差贡献率为81.408%,各诊断变量在所属公因子上的载荷值为0.770~0.918。聚类分析结果显示,共将OSO患者分为3类。不同类别人群四肢骨骼肌指数、握力、BF%、BMDL1~4、BMD髋部、BMD股骨颈、BMI、腰围比较,差异均有统计学意义(P<0.05)。其中第1类人群的BMDL1~4、BMD髋部、BMD股骨颈均低于其他两类人群(P<0.05);第2类人群的BMI和腰围均低于其他两类人群(P<0.05);第3类人群的四肢骨骼肌指数、握力和BMD均高于其他两类人群,BF%低于其他两类人群(P<0.05)。不同类别人群性别、受教育程度、个人月收入分布、总胆固醇(TC)、高密度脂蛋白胆固醇(HDL-C)、尿酸(UA)、肌酐(Cr)水平比较,差异有统计学意义(P<0.05)。第1类人群中本科以下学历者占比高于第3类人群(P<0.017);第2类人群TC水平高于第3类人群(P<0.05);第3类人群个人月收入≥5 000元者占比,以及UA、Cr水平均高于其他两类人群,女性占比低于其他两类人群(P<0.05或P<0.017)。结论 可从骨质疏松、肌肉与体脂、肥胖3个方面对OSO诊断变量进行概括和解释;OSO患者具有不同的结构特征。应用多元统计学方法研究OSO患者的结构特征,有助于实现对不同类型OSO患者的个体化管理。},\n\turl = {https://kns.cnki.net/kcms2/article/abstract?v=Vs3rztogjcWwUSjjMBY0aZhiQJ3vDP7Aox7PNqQ394TMU1Yz3Ef1pZKu4uZnfJBxuZcg-7QcD6RgDnGu-2ygOBXnJYSTg1P48IMNOcNew8ukjlM3CrZCP6qa--FkBU0pO5vqXSTzCnPdQuQlx74PnEvnHFvEmJukTjWZZQGsG-MmTursr3lZ6N-nqrR_b1OA&uniplatform=NZKPT&language=CHS},\n\tvolume = {25},\n\tnumber = {22},\n\tpages = {2733-2739+2745},\n\tissn = {1007-9572},\n\tnote = {CNKI}\n}",
      "source_files": [
        "CNKI-20260403233112547.enw"
      ],
      "source_keys": [
        "endnote_000117"
      ],
      "merged_from": [],
      "status": "unprocessed"
    },
    {
      "paper_id": "paper_000117",
      "entry_type": "article",
      "title": "老年人居家医疗护理服务需求等级评估工具研究现状",
      "authors": [
        "李航",
        "刘素珍"
      ],
      "year": 2022,
      "journal": "医学与社会",
      "doi": "10.13723/j.yxysh.2022.06.002",
      "abstract": "居家医疗护理服务已成为部分失能、半失能老年慢性病患者的刚性需求。如何将此类患者的居家医疗护理服务需求分级,以提供有针对的个性化服务是目前面临的挑战。通过文献回顾国内外常用的需求等级评估工具,包括各评估内容和指标、评判标准和用法、工具信度和效度以及其应用状况时发现,国内相关评估工具主要针对老年人设计,注重其功能状态评估,以失能水平来评价患者日常生活照料需求及其程度,未涉及具体的居家医疗护理服务内容;而国外相关工具在功能状态评估基础上,更注重对患者具体医疗护理服务需求的评估,其评估内容全面,适用人群也不局限于老年人,对提供居家医疗护理服务有更强的指导价值,但其条目繁多,对评估技术要求高且相对耗时。建议根据国内基层医疗卫生特点精选和量化居家医疗护理服务需求评估指标,构建能确实反映老年慢性病患者居家医疗护理服务需求等级评估工具,并利用信息技术实现需求等级的动态监测。",
      "keywords": [
        "慢性病",
        "居家医疗护理",
        "护理需求",
        "等级评估",
        "老年人"
      ],
      "normalized_title": "老年人居家医疗护理服务需求等级评估工具研究现状",
      "raw_bibtex": "@ARTICLE{10.13723/j.yxysh.2022.06.002,\n\tauthor = {李航 and 刘素珍},\n\ttitle = {老年人居家医疗护理服务需求等级评估工具研究现状},\n\tjournal = {医学与社会},\n\tyear = {2022},\n\tkeywords = {慢性病;居家医疗护理;护理需求;等级评估;老年人},\n\tabstract = {居家医疗护理服务已成为部分失能、半失能老年慢性病患者的刚性需求。如何将此类患者的居家医疗护理服务需求分级,以提供有针对的个性化服务是目前面临的挑战。通过文献回顾国内外常用的需求等级评估工具,包括各评估内容和指标、评判标准和用法、工具信度和效度以及其应用状况时发现,国内相关评估工具主要针对老年人设计,注重其功能状态评估,以失能水平来评价患者日常生活照料需求及其程度,未涉及具体的居家医疗护理服务内容;而国外相关工具在功能状态评估基础上,更注重对患者具体医疗护理服务需求的评估,其评估内容全面,适用人群也不局限于老年人,对提供居家医疗护理服务有更强的指导价值,但其条目繁多,对评估技术要求高且相对耗时。建议根据国内基层医疗卫生特点精选和量化居家医疗护理服务需求评估指标,构建能确实反映老年慢性病患者居家医疗护理服务需求等级评估工具,并利用信息技术实现需求等级的动态监测。},\n\tdoi = {10.13723/j.yxysh.2022.06.002},\n\turl = {https://link.cnki.net/doi/10.13723/j.yxysh.2022.06.002},\n\tvolume = {35},\n\tnumber = {06},\n\tpages = {7-11},\n\tissn = {1006-5563},\n\tnote = {CNKI}\n}",
      "source_files": [
        "CNKI-20260403233112547.enw"
      ],
      "source_keys": [
        "10.13723/j.yxysh.2022.06.002"
      ],
      "merged_from": [],
      "status": "unprocessed"
    },
    {
      "paper_id": "paper_000118",
      "entry_type": "article",
      "title": "人工智能在护理领域的应用现状及发展前景",
      "authors": [
        "周瑶群",
        "方荣华"
      ],
      "year": 2022,
      "journal": "护理研究",
      "doi": null,
      "abstract": "总结人工智能在护理领域的应用现状,从临床工作应用、老年照护、协助护理诊断、管理慢性病4个方面进行分析,对其在护理领域的发展前景进行展望,探索人工智能在护理领域应用的挑战与困境。",
      "keywords": [
        "人工智能",
        "大数据",
        "老年人",
        "慢性病",
        "护理",
        "综述"
      ],
      "normalized_title": "人工智能在护理领域的应用现状及发展前景",
      "raw_bibtex": "@ARTICLE{endnote_000119,\n\tauthor = {周瑶群 and 方荣华},\n\ttitle = {人工智能在护理领域的应用现状及发展前景},\n\tjournal = {护理研究},\n\tyear = {2022},\n\tkeywords = {人工智能;大数据;老年人;慢性病;护理;综述},\n\tabstract = {总结人工智能在护理领域的应用现状,从临床工作应用、老年照护、协助护理诊断、管理慢性病4个方面进行分析,对其在护理领域的发展前景进行展望,探索人工智能在护理领域应用的挑战与困境。},\n\turl = {https://kns.cnki.net/kcms2/article/abstract?v=Vs3rztogjcXcR6X-NAfUBlM4lQgfKpaILLy252w_TXl0acp0asHCbm5x4INFjsxs73awI3zG_uyM4tCEkrrmpyTAB82UHUgo2vSK0P4344Z8lb07u6ghlNKZIlP9VDGcqxpKFqGITHhN_l_UdUk0fXXRBnoW4HTNSKmdOrHRV9VVpcd0UrJU45vj4bsmD-rh&uniplatform=NZKPT&language=CHS},\n\tvolume = {36},\n\tnumber = {06},\n\tpages = {1053-1057},\n\tissn = {1009-6493},\n\tnote = {CNKI}\n}",
      "source_files": [
        "CNKI-20260403233112547.enw"
      ],
      "source_keys": [
        "endnote_000119"
      ],
      "merged_from": [],
      "status": "unprocessed"
    },
    {
      "paper_id": "paper_000119",
      "entry_type": "article",
      "title": "住院老年慢性病病人治疗负担现状及其影响因素研究",
      "authors": [
        "赵莹",
        "王晨",
        "孙玉倩",
        "李淑杏"
      ],
      "year": 2022,
      "journal": "现代预防医学",
      "doi": null,
      "abstract": "目的 探讨住院老年慢性病病人治疗负担的现状及其影响因素。方法 采用便利抽样法,应用一般资料调查表、治疗负担量表、健康素养量表、Barthel指数评定量表对366名住院老年慢性病病人进行问卷调查,运用Mann-Whitney U秩和检验/Kruskal-Wallis H秩和检验、Spearman相关分析、K类中心聚类分析、有序logistic回归分析进行统计分析。结果 住院老年慢性病病人的治疗负担总分为(31.96±18.27)分。低度治疗负担占48.1%、中度治疗负担占42.6%、重度治疗负担占9.3%。有序logistic回归分析显示,自费(OR=21.933,95%CI:1.045~5.132)、重度功能障碍(OR=14.397,95%CI:0.437~4.897)、信息获取能力(OR=0.879,95%CI:-0.185~-0.073)和改善健康意愿(OR=0.859,95%CI:-0.244~-0.059)是老年慢性病病人治疗负担的影响因素(P<0.05)。结论 老年慢性病病人的治疗负担以轻度治疗负担为主,临床工作者应降低病人为遵医嘱治疗所投入的时间和努力,针对不同生活能力的病人给予康复指导和心理安慰,增强病人对健康管理和疾病知识的教育,以达到减轻老年慢性病病人治疗负担的目的。",
      "keywords": [
        "治疗负担",
        "健康素养",
        "老年",
        "慢性病"
      ],
      "normalized_title": "住院老年慢性病病人治疗负担现状及其影响因素研究",
      "raw_bibtex": "@ARTICLE{endnote_000120,\n\tauthor = {赵莹 and 王晨 and 孙玉倩 and 李淑杏},\n\ttitle = {住院老年慢性病病人治疗负担现状及其影响因素研究},\n\tjournal = {现代预防医学},\n\tyear = {2022},\n\tkeywords = {治疗负担;健康素养;老年;慢性病},\n\tabstract = {目的 探讨住院老年慢性病病人治疗负担的现状及其影响因素。方法 采用便利抽样法,应用一般资料调查表、治疗负担量表、健康素养量表、Barthel指数评定量表对366名住院老年慢性病病人进行问卷调查,运用Mann-Whitney U秩和检验/Kruskal-Wallis H秩和检验、Spearman相关分析、K类中心聚类分析、有序logistic回归分析进行统计分析。结果 住院老年慢性病病人的治疗负担总分为(31.96±18.27)分。低度治疗负担占48.1%、中度治疗负担占42.6%、重度治疗负担占9.3%。有序logistic回归分析显示,自费(OR=21.933,95%CI:1.045~5.132)、重度功能障碍(OR=14.397,95%CI:0.437~4.897)、信息获取能力(OR=0.879,95%CI:-0.185~-0.073)和改善健康意愿(OR=0.859,95%CI:-0.244~-0.059)是老年慢性病病人治疗负担的影响因素(P<0.05)。结论 老年慢性病病人的治疗负担以轻度治疗负担为主,临床工作者应降低病人为遵医嘱治疗所投入的时间和努力,针对不同生活能力的病人给予康复指导和心理安慰,增强病人对健康管理和疾病知识的教育,以达到减轻老年慢性病病人治疗负担的目的。},\n\turl = {https://kns.cnki.net/kcms2/article/abstract?v=Vs3rztogjcXtJj5QMgCPkx7sFWtL0dFOJ8Pl6zZB3CTI9X9tuZC105QulHiCMoy6jnZAiGnuUqzfV4IVWOmwJcAx-XEy6VcytyeuzbFBxyenwrFpdgLQl-DbgTSQLdXzJQq61I7VZzAdJjOGRBKrJ5IFHuFYIdPK4Fy0gcPgPnglvXOpQUxghnLlyubpq32q&uniplatform=NZKPT&language=CHS},\n\tvolume = {49},\n\tnumber = {06},\n\tpages = {1078-1081+1117},\n\tissn = {1003-8507},\n\tnote = {CNKI}\n}",
      "source_files": [
        "CNKI-20260403233112547.enw"
      ],
      "source_keys": [
        "endnote_000120"
      ],
      "merged_from": [],
      "status": "unprocessed"
    },
    {
      "paper_id": "paper_000120",
      "entry_type": "article",
      "title": "健康城市与疗愈环境",
      "authors": [
        "杜宏武",
        "李树华",
        "姜斌",
        "陈筝",
        "龙灏",
        "袁晓梅"
      ],
      "year": 2022,
      "journal": "南方建筑",
      "doi": null,
      "abstract": "2016年10月,中共中央、国务院印发《“健康中国2030”规划纲要》,提出要“把健康融入城乡规划、建设、治理的全过程,促进城市与人民健康协调发展”。作为健康中国建设不可或缺的部分,疗愈环境对人类生理和心理健康的价值已得到多方面研究的证实,早期心理医学、康复医学的成果逐渐影响了风景园林、城市规划和建筑学。在当代高密度城市人居,尤其是2020年新冠疫情爆发以来,疗愈环境愈发凸显其重要价值。近年来学者们从不同层级蓝绿空间、自然元素等视角,拓展和深化了相关研究的内容,不断尝试运用新的实验手段,成果斐然。本刊编辑部以“健康城市与疗愈环境”为主题组织学术笔谈,邀请了六位不同背景的学者就疗愈环境议题做集中并各有侧重的探讨。李树华从城市尺度探讨绿色和健康的联系,认为城市是人类聚集和生活的场所,随着人类的进化不断发展。理想城市应当符合人类对美好生活的向往,既能满足生态可持续的绿色发展需求,也能提供有益人类健康的适宜人居环境。“绿康城市”论就是当今缓解“城市病”与“城市人群病”的理想模式之一,而日本东京城市中心“大手町之森”正是“绿康城市”论的实践先驱案例。基于人、自然和城市三者之间的关系,追溯欧美、日本与中国理想城市的发展历程,并对进行建设“绿康城市”实践时应坚持的原则与构成要素进行探讨。美国新冠病毒感染率呈现的显著种族差异反映出健康公义问题。姜斌等就此提出假设:绿色空间覆盖率更高的地区感染率种族差异会明显减少。本研究在控制了社会经济特征变量与慢性疾病变量后,通过多重线性回归模型来测量新冠感染率种族差异与绿色空间变量的关联性。最后得出结论:在县级尺度,更高的绿色空间覆盖率会令种族间的新冠感染率差异显著减少,其中有四类绿色空间类型具有显著影响。最终我们建立了一个周边机制与五个核心机制来解释这种关联性。杜宏武等认为高密度城市日常生活场景满足人的恢复性体验尤为重要,新冠疫情强化了这种需求。良好设计营造的办公楼、住宅两种空中花园都有恢复性效益,但其空间形态、影响因素、作用机制有明显不同。为增进空中花园的恢复性效益,其空间位置、组合与空间联系应合理布置;探索其恢复性效益的影响因素,如视觉通达性、空间层次、绿视率等,提升其空间品质;构建支持性环境,强化复合功能,提高参与度和使用率。陈筝认为城市中的绿色接触对促进城市居民健康非常重要。在实际项目中,高绿街道的健康效益的实现,需要充分考虑街道本身的功能和使用。陈筝结合成都公园城市的街道改造建设,通过行为实验采集了40位被试在具体街道场景中步行、商业设施使用、街旁绿地游憩的选择偏好,以及他们对于街道环境的第一印象和分维度评价。与此同时,通过SMI Redn Professional桌面式眼动仪记录了被试在做相关选择或评价时的注视情况。为健康街道的设计提供决策支持。龙灏尝试梳理、阐述了循证设计在康复花园设计与建设中的具体运用。认为作为CCRC型养老社区中重要的心理生理康复空间,康复花园需要以循证设计为方法,通过科学清晰的方式,提升自身的心理疏导功能,伴随疫情下医养机构封闭化管理的常态化,老年居民的心理健康、抑郁焦虑等等问题愈加突出,希望本文能为未来的康复花园设计思考提供依据与帮助,为新形势下CCRC型养老社区提供切实可行的心理康复空间。围绕WHO老年友好城市框架,袁晓梅提出“基于健康管理的适老社区环境”概念。从“舒适安全”“促进活动”“亲近自然”“互动联系”四个层面,建构“老人+环境+生活”的关键技术体系。旨在将医学的康复治疗融入老年人日常的户外活动,为提升老年人口健康寿命提供有效的环境解决方案。结合袁晓梅教授团队初步的研究成果与循证实践,说明相关技术的健康绩效与应用潜力。",
      "keywords": [
        "健康城市",
        "疗愈环境",
        "绿康城市",
        "健康公义",
        "健康效益",
        "康复社区"
      ],
      "normalized_title": "健康城市与疗愈环境",
      "raw_bibtex": "@ARTICLE{endnote_000121,\n\tauthor = {杜宏武 and 李树华 and 姜斌 and 陈筝 and 龙灏 and 袁晓梅},\n\ttitle = {健康城市与疗愈环境},\n\tjournal = {南方建筑},\n\tyear = {2022},\n\tkeywords = {健康城市;疗愈环境;绿康城市;健康公义;健康效益;康复社区},\n\tabstract = {2016年10月,中共中央、国务院印发《“健康中国2030”规划纲要》,提出要“把健康融入城乡规划、建设、治理的全过程,促进城市与人民健康协调发展”。作为健康中国建设不可或缺的部分,疗愈环境对人类生理和心理健康的价值已得到多方面研究的证实,早期心理医学、康复医学的成果逐渐影响了风景园林、城市规划和建筑学。在当代高密度城市人居,尤其是2020年新冠疫情爆发以来,疗愈环境愈发凸显其重要价值。近年来学者们从不同层级蓝绿空间、自然元素等视角,拓展和深化了相关研究的内容,不断尝试运用新的实验手段,成果斐然。本刊编辑部以“健康城市与疗愈环境”为主题组织学术笔谈,邀请了六位不同背景的学者就疗愈环境议题做集中并各有侧重的探讨。李树华从城市尺度探讨绿色和健康的联系,认为城市是人类聚集和生活的场所,随着人类的进化不断发展。理想城市应当符合人类对美好生活的向往,既能满足生态可持续的绿色发展需求,也能提供有益人类健康的适宜人居环境。“绿康城市”论就是当今缓解“城市病”与“城市人群病”的理想模式之一,而日本东京城市中心“大手町之森”正是“绿康城市”论的实践先驱案例。基于人、自然和城市三者之间的关系,追溯欧美、日本与中国理想城市的发展历程,并对进行建设“绿康城市”实践时应坚持的原则与构成要素进行探讨。美国新冠病毒感染率呈现的显著种族差异反映出健康公义问题。姜斌等就此提出假设:绿色空间覆盖率更高的地区感染率种族差异会明显减少。本研究在控制了社会经济特征变量与慢性疾病变量后,通过多重线性回归模型来测量新冠感染率种族差异与绿色空间变量的关联性。最后得出结论:在县级尺度,更高的绿色空间覆盖率会令种族间的新冠感染率差异显著减少,其中有四类绿色空间类型具有显著影响。最终我们建立了一个周边机制与五个核心机制来解释这种关联性。杜宏武等认为高密度城市日常生活场景满足人的恢复性体验尤为重要,新冠疫情强化了这种需求。良好设计营造的办公楼、住宅两种空中花园都有恢复性效益,但其空间形态、影响因素、作用机制有明显不同。为增进空中花园的恢复性效益,其空间位置、组合与空间联系应合理布置;探索其恢复性效益的影响因素,如视觉通达性、空间层次、绿视率等,提升其空间品质;构建支持性环境,强化复合功能,提高参与度和使用率。陈筝认为城市中的绿色接触对促进城市居民健康非常重要。在实际项目中,高绿街道的健康效益的实现,需要充分考虑街道本身的功能和使用。陈筝结合成都公园城市的街道改造建设,通过行为实验采集了40位被试在具体街道场景中步行、商业设施使用、街旁绿地游憩的选择偏好,以及他们对于街道环境的第一印象和分维度评价。与此同时,通过SMI Redn Professional桌面式眼动仪记录了被试在做相关选择或评价时的注视情况。为健康街道的设计提供决策支持。龙灏尝试梳理、阐述了循证设计在康复花园设计与建设中的具体运用。认为作为CCRC型养老社区中重要的心理生理康复空间,康复花园需要以循证设计为方法,通过科学清晰的方式,提升自身的心理疏导功能,伴随疫情下医养机构封闭化管理的常态化,老年居民的心理健康、抑郁焦虑等等问题愈加突出,希望本文能为未来的康复花园设计思考提供依据与帮助,为新形势下CCRC型养老社区提供切实可行的心理康复空间。围绕WHO老年友好城市框架,袁晓梅提出“基于健康管理的适老社区环境”概念。从“舒适安全”“促进活动”“亲近自然”“互动联系”四个层面,建构“老人+环境+生活”的关键技术体系。旨在将医学的康复治疗融入老年人日常的户外活动,为提升老年人口健康寿命提供有效的环境解决方案。结合袁晓梅教授团队初步的研究成果与循证实践,说明相关技术的健康绩效与应用潜力。},\n\turl = {https://kns.cnki.net/kcms2/article/abstract?v=Vs3rztogjcWQyGFXErR-fKqBrb57hFLSuBSXwnwOoORCX8wiuEiRoHhAasRtC4fg0ml1iTkhJOccZMtwc-A8Hr7w9PegoezdpSG99w8neUP-C6wTxIH1E-bKnWn_LTG2eSrSADXptZNUAQvRDbYAyP2BnEUoB5Z1NKfNmVBI1CPi0HE39_5CHmw8auC92Qlf&uniplatform=NZKPT&language=CHS},\n\tnumber = {03},\n\tpages = {1-8},\n\tissn = {1000-0232},\n\tnote = {CNKI}\n}",
      "source_files": [
        "CNKI-20260403233112547.enw"
      ],
      "source_keys": [
        "endnote_000121"
      ],
      "merged_from": [],
      "status": "unprocessed"
    }
  ]
}
