{
  "batch_id": "batch_0010",
  "paper_count": 10,
  "paper_ids": [
    "paper_000091",
    "paper_000092",
    "paper_000093",
    "paper_000094",
    "paper_000095",
    "paper_000096",
    "paper_000097",
    "paper_000098",
    "paper_000099",
    "paper_000100"
  ],
  "papers": [
    {
      "paper_id": "paper_000091",
      "entry_type": "article",
      "title": "Arc Erosion Behaviors of Pantograph of High-Speed Train During Its Rise and Fall Processes",
      "authors": [
        "Pan, L.",
        "Yi, X.",
        "Xing, T.",
        "Yu, Z.",
        "Yang, C.",
        "Yu, Q.",
        "Zhu, X.",
        "Zhuang, N.",
        "Jin, A.",
        "Cui, Y.",
        "Feng, T.",
        "Chen, J.",
        "Yan, W."
      ],
      "year": 2025,
      "journal": "IEEE Access",
      "doi": "10.1109/access.2025.3612260",
      "abstract": "Arc melting pools are generated when the pantograph and catenary (PAC) are offline during the rise and fall of the pantograph. They can lead to the material damage, accelerated wear, increased splashing, and exacerbated PAC fatigue through the thermal cycling, shortening its service life. In this paper, the voltage and current are measured by a high-speed PAC experimental platform when the PAC occur the offline discharge. And the arc erosion images are obtained using a scanning electron microscope. Based on the principle of the magnetohydrodynamics, a simulation model of the PAC arc is established and its correctness is verified by comparing the experimental data. The distribution of the heat flow input density of the arc is obtained by adopting the moving mesh technique and coupling the actual auto-transformer (AT) traction grid circuit. Meanwhile, the melting solidification model and evaporation sublimation model are introduced to study the behavior of the material erosion by the arc when the pantograph rises and lowers. When the PAC offline discharge occurs during the rise of the pantograph, the heat flow density is concentrated and the temperatures of the contact line and pantograph are 3550 K and 4290 K, respectively. The melting pool is of a deep and narrow type. Its depth is 1.71 mm, which is 80% more than that during the fall of the pantograph. While its width decreases by 17.48% compared with that during the fall of the pantograph, which increases the risk of the localized overheating and thermal stresses. As the pantograph falls, the density of the heat flow decreases and the temperature of the contact point is lowered. The melting pool is shallow and wide, making it more susceptible to splashing and accelerating the wear. The increased temperature in the melting pool triggers the Marangoni effect, which leads to the eddy currents. They increase the instability and spattering on the surface of the pantograph, accelerating the material damage. The innovation of this paper lies in the integration of the arc model, erosion model, and AT traction circuits, and the introduction of the Marangoni force, evaporation-sublimation behaviors, and moving mesh technology, to systematically study the PAC erosion behaviors during the rise and fall of the pantograph. Its purpose is to provide theoretical support for the selection of the PAC materials, their structural design, and preventive maintenance. © 2013 IEEE.",
      "keywords": [],
      "normalized_title": "arc erosion behaviors of pantograph of high speed train during its rise and fall processes",
      "raw_bibtex": "@ARTICLE{10.1109/ACCESS.2025.3612260,\n\tauthor = {Pan, L. and Yi, X. and Xing, T. and Yu, Z. and Yang, C. and Yu, Q. and Zhu, X. and Zhuang, N. and Jin, A. and Cui, Y. and Feng, T. and Chen, J. and Yan, W.},\n\ttitle = {Arc Erosion Behaviors of Pantograph of High-Speed Train During Its Rise and Fall Processes},\n\tjournal = {IEEE Access},\n\tyear = {2025},\n\tabstract = {Arc melting pools are generated when the pantograph and catenary (PAC) are offline during the rise and fall of the pantograph. They can lead to the material damage, accelerated wear, increased splashing, and exacerbated PAC fatigue through the thermal cycling, shortening its service life. In this paper, the voltage and current are measured by a high-speed PAC experimental platform when the PAC occur the offline discharge. And the arc erosion images are obtained using a scanning electron microscope. Based on the principle of the magnetohydrodynamics, a simulation model of the PAC arc is established and its correctness is verified by comparing the experimental data. The distribution of the heat flow input density of the arc is obtained by adopting the moving mesh technique and coupling the actual auto-transformer (AT) traction grid circuit. Meanwhile, the melting solidification model and evaporation sublimation model are introduced to study the behavior of the material erosion by the arc when the pantograph rises and lowers. When the PAC offline discharge occurs during the rise of the pantograph, the heat flow density is concentrated and the temperatures of the contact line and pantograph are 3550 K and 4290 K, respectively. The melting pool is of a deep and narrow type. Its depth is 1.71 mm, which is 80% more than that during the fall of the pantograph. While its width decreases by 17.48% compared with that during the fall of the pantograph, which increases the risk of the localized overheating and thermal stresses. As the pantograph falls, the density of the heat flow decreases and the temperature of the contact point is lowered. The melting pool is shallow and wide, making it more susceptible to splashing and accelerating the wear. The increased temperature in the melting pool triggers the Marangoni effect, which leads to the eddy currents. They increase the instability and spattering on the surface of the pantograph, accelerating the material damage. The innovation of this paper lies in the integration of the arc model, erosion model, and AT traction circuits, and the introduction of the Marangoni force, evaporation-sublimation behaviors, and moving mesh technology, to systematically study the PAC erosion behaviors during the rise and fall of the pantograph. Its purpose is to provide theoretical support for the selection of the PAC materials, their structural design, and preventive maintenance. © 2013 IEEE.},\n\tdoi = {10.1109/ACCESS.2025.3612260},\n\turl = {https://www.scopus.com/inward/record.uri?eid=2-s2.0-105017098551&doi=10.1109%2FACCESS.2025.3612260&partnerID=40&md5=1da83e3405e5aea70257bfdf3fb7e304},\n\tvolume = {13},\n\tpages = {165144-165156},\n\tnote = {Export Date: 30 March 2026; Cited By: 2 ER -; Article},\n\ttype = {Article},\n\tsource = {Scopus}\n}",
      "source_files": [
        "scopus_export_Mar 30-2026_b9a59ff7-ed41-4872-a208-e0fc4046c226.ris"
      ],
      "source_keys": [
        "10.1109/ACCESS.2025.3612260"
      ],
      "merged_from": [],
      "status": "unprocessed"
    },
    {
      "paper_id": "paper_000092",
      "entry_type": "article",
      "title": "Study of Slide Ablation Characteristics During Pantograph Lowering Based on Simulation and Arc Voltage Measurements",
      "authors": [
        "Wang, X.",
        "Duan, F.",
        "Song, Y.",
        "Liu, Z.",
        "Chen, L."
      ],
      "year": 2026,
      "journal": "IEEE Transactions on Instrumentation and Measurement",
      "doi": "10.1109/tim.2025.3650294",
      "abstract": "The process of pantograph lowering in electric locomotives generates intense transient arcing, which significantly influences the service life of the pantograph–catenary (PC) contact pair. This article investigates slide ablation during pantograph lowering by incorporating heat dissipation from material evaporation, a factor not addressed in prior studies. First, a high-precision arc voltage acquisition system was developed and implemented under real railway conditions. This system served as the basis for validating the proposed multiphysics-coupled transient arcing model. Subsequently, an ablation model was established to account for the effect of material evaporation on surface temperature evolution under transient arcing. Then, numerical simulations were conducted to reveal the temperature field distribution on the slide surface. Finally, the effects of pantograph-lowering voltages, pantograph-lowering speeds, and ambient wind speeds on the slide ablation were systematically analyzed. The results indicate that reducing the pantograph-lowering voltage and increasing the pantograph-lowering speed can effectively mitigate slide surface ablation. Furthermore, the transient arcing produces an arc-shaped ablation pit on the slide surface, with the peak temperature stabilizing at approximately 4000 K, close to the carbon sublimation point. © 1963-2012 IEEE.",
      "keywords": [],
      "normalized_title": "study of slide ablation characteristics during pantograph lowering based on simulation and arc voltage measurements",
      "raw_bibtex": "@ARTICLE{10.1109/TIM.2025.3650294,\n\tauthor = {Wang, X. and Duan, F. and Song, Y. and Liu, Z. and Chen, L.},\n\ttitle = {Study of Slide Ablation Characteristics During Pantograph Lowering Based on Simulation and Arc Voltage Measurements},\n\tjournal = {IEEE Transactions on Instrumentation and Measurement},\n\tyear = {2026},\n\tabstract = {The process of pantograph lowering in electric locomotives generates intense transient arcing, which significantly influences the service life of the pantograph–catenary (PC) contact pair. This article investigates slide ablation during pantograph lowering by incorporating heat dissipation from material evaporation, a factor not addressed in prior studies. First, a high-precision arc voltage acquisition system was developed and implemented under real railway conditions. This system served as the basis for validating the proposed multiphysics-coupled transient arcing model. Subsequently, an ablation model was established to account for the effect of material evaporation on surface temperature evolution under transient arcing. Then, numerical simulations were conducted to reveal the temperature field distribution on the slide surface. Finally, the effects of pantograph-lowering voltages, pantograph-lowering speeds, and ambient wind speeds on the slide ablation were systematically analyzed. The results indicate that reducing the pantograph-lowering voltage and increasing the pantograph-lowering speed can effectively mitigate slide surface ablation. Furthermore, the transient arcing produces an arc-shaped ablation pit on the slide surface, with the peak temperature stabilizing at approximately 4000 K, close to the carbon sublimation point. © 1963-2012 IEEE.},\n\tdoi = {10.1109/TIM.2025.3650294},\n\turl = {https://www.scopus.com/inward/record.uri?eid=2-s2.0-105026625393&doi=10.1109%2FTIM.2025.3650294&partnerID=40&md5=f82d05bf5c55b9eda6d0d28dba8f1ca9},\n\tvolume = {75},\n\tnote = {Export Date: 30 March 2026; Cited By: 0 ER -; Article},\n\ttype = {Article},\n\tsource = {Scopus}\n}",
      "source_files": [
        "scopus_export_Mar 30-2026_b9a59ff7-ed41-4872-a208-e0fc4046c226.ris"
      ],
      "source_keys": [
        "10.1109/TIM.2025.3650294"
      ],
      "merged_from": [],
      "status": "unprocessed"
    },
    {
      "paper_id": "paper_000093",
      "entry_type": "article",
      "title": "High-precision vision-based measurement of key pantograph parameters for high-speed trains using Siamese networks and MOTFSE",
      "authors": [
        "Wei, X.",
        "Zhao, C.",
        "Liu, X.",
        "Wu, D.",
        "Tang, Q."
      ],
      "year": 2026,
      "journal": "Journal of Control and Decision",
      "doi": "10.1080/23307706.2025.2569552",
      "abstract": "The pantograph transfers electric energy from the catenary to high-speed trains and is critical for electrified railways. However, excessive motion can cause pantograph-catenary malfunctions, including catenary breaks, arcing, and mechanical damage to the pantograph. Therefore, detecting pantograph head motion is crucial for reliable high-speed train operation. This paper employs an improved Siamese network to measure its horizontal/vertical displacement and estimate the dynamic envelope. A multi-branch Siamese network is also developed to extract displacements of multiple targets for stagger value estimation. Additionally, the proposed MOTFSE algorithm (Multi-Object Tracking and Optical Flow Speed Estimation) fuses tracking and optical flow results to estimate the vertical vibration speed. Experimental results show the proposed algorithm achieves over 90% tracking accuracy and precision for the pantograph head. It enables accurate measurement of the pantograph's dynamic envelope, contact wire stagger value, and head vertical oscillation velocity, offering a viable solution for practical application. © 2025 Northeastern University, China.",
      "keywords": [],
      "normalized_title": "high precision vision based measurement of key pantograph parameters for high speed trains using siamese networks and motfse",
      "raw_bibtex": "@ARTICLE{10.1080/23307706.2025.2569552,\n\tauthor = {Wei, X. and Zhao, C. and Liu, X. and Wu, D. and Tang, Q.},\n\ttitle = {High-precision vision-based measurement of key pantograph parameters for high-speed trains using Siamese networks and MOTFSE},\n\tjournal = {Journal of Control and Decision},\n\tyear = {2026},\n\tabstract = {The pantograph transfers electric energy from the catenary to high-speed trains and is critical for electrified railways. However, excessive motion can cause pantograph-catenary malfunctions, including catenary breaks, arcing, and mechanical damage to the pantograph. Therefore, detecting pantograph head motion is crucial for reliable high-speed train operation. This paper employs an improved Siamese network to measure its horizontal/vertical displacement and estimate the dynamic envelope. A multi-branch Siamese network is also developed to extract displacements of multiple targets for stagger value estimation. Additionally, the proposed MOTFSE algorithm (Multi-Object Tracking and Optical Flow Speed Estimation) fuses tracking and optical flow results to estimate the vertical vibration speed. Experimental results show the proposed algorithm achieves over 90% tracking accuracy and precision for the pantograph head. It enables accurate measurement of the pantograph's dynamic envelope, contact wire stagger value, and head vertical oscillation velocity, offering a viable solution for practical application. © 2025 Northeastern University, China.},\n\tdoi = {10.1080/23307706.2025.2569552},\n\turl = {https://www.scopus.com/inward/record.uri?eid=2-s2.0-105022755562&doi=10.1080%2F23307706.2025.2569552&partnerID=40&md5=fe6627d43cbddddf287efc8b091d4ca2},\n\tvolume = {13},\n\tnumber = {2},\n\tpages = {239-255},\n\tnote = {Export Date: 30 March 2026; Cited By: 0 ER -; Article},\n\ttype = {Article},\n\tsource = {Scopus}\n}",
      "source_files": [
        "scopus_export_Mar 30-2026_b9a59ff7-ed41-4872-a208-e0fc4046c226.ris"
      ],
      "source_keys": [
        "10.1080/23307706.2025.2569552"
      ],
      "merged_from": [],
      "status": "unprocessed"
    },
    {
      "paper_id": "paper_000094",
      "entry_type": "article",
      "title": "A novel arc detection and identification method in pantograph-catenary system based on deep learning",
      "authors": [
        "Yan, Y.",
        "Liu, H.",
        "Gan, L.",
        "Zhu, R."
      ],
      "year": 2025,
      "journal": "Scientific Reports",
      "doi": "10.1038/s41598-025-88109-x",
      "abstract": "Arc detection is crucial for ensuring the safe operation of power systems, where timely and accurate detection of arcs can prevent potential hazards such as fires, equipment damage, or system failures. Traditional arc detection methods, while functional, often suffer from low detection accuracy and high computational complexity, especially in complex operational environments. This limitation is particularly problematic in real-time monitoring and the efficient operation of power systems. In order to solve these problems, this paper proposes a method of arc detection based on deep learning, called arc multi-scene detection (ArcMSD), which leverages deep learning techniques to address these challenges. The primary distinction of this method lies in its enhancement of the Inception V3 model. This paper has redesigned the original Inception module by incorporating a guided anchor mechanism, an attention mechanism, and upsampling techniques to optimize detection performance. The improved Inception V3 network uses an attention mechanism to allow the model to focus on arc features in complex backgrounds, which can also prevent the model from overfitting. It performs upsampling and fusion with low-level features in the model. The fused features have better arc discrimination capabilities than the original input features, which better improves the accuracy of the model. In order to adapt to arcs with large size differences and improve detection efficiency, the guided anchor is selected to adjust the anchor generation algorithm. In terms of dataset, continuous frame images are intercepted from the video of Integrated Supervision and Control System (ISCS), and image preprocessing operations are performed to improve the model’s detection accuracy of pantograph arcs. Experimental results show that the mean Average Precision (mAP) of the deep learning model proposed in this article is 95.4%, which is far better than other models, thus verify the method’s efficacy. © The Author(s) 2025.",
      "keywords": [],
      "normalized_title": "a novel arc detection and identification method in pantograph catenary system based on deep learning",
      "raw_bibtex": "@ARTICLE{10.1038/s41598-025-88109-x,\n\tauthor = {Yan, Y. and Liu, H. and Gan, L. and Zhu, R.},\n\ttitle = {A novel arc detection and identification method in pantograph-catenary system based on deep learning},\n\tjournal = {Scientific Reports},\n\tyear = {2025},\n\tabstract = {Arc detection is crucial for ensuring the safe operation of power systems, where timely and accurate detection of arcs can prevent potential hazards such as fires, equipment damage, or system failures. Traditional arc detection methods, while functional, often suffer from low detection accuracy and high computational complexity, especially in complex operational environments. This limitation is particularly problematic in real-time monitoring and the efficient operation of power systems. In order to solve these problems, this paper proposes a method of arc detection based on deep learning, called arc multi-scene detection (ArcMSD), which leverages deep learning techniques to address these challenges. The primary distinction of this method lies in its enhancement of the Inception V3 model. This paper has redesigned the original Inception module by incorporating a guided anchor mechanism, an attention mechanism, and upsampling techniques to optimize detection performance. The improved Inception V3 network uses an attention mechanism to allow the model to focus on arc features in complex backgrounds, which can also prevent the model from overfitting. It performs upsampling and fusion with low-level features in the model. The fused features have better arc discrimination capabilities than the original input features, which better improves the accuracy of the model. In order to adapt to arcs with large size differences and improve detection efficiency, the guided anchor is selected to adjust the anchor generation algorithm. In terms of dataset, continuous frame images are intercepted from the video of Integrated Supervision and Control System (ISCS), and image preprocessing operations are performed to improve the model’s detection accuracy of pantograph arcs. Experimental results show that the mean Average Precision (mAP) of the deep learning model proposed in this article is 95.4%, which is far better than other models, thus verify the method’s efficacy. © The Author(s) 2025.},\n\tdoi = {10.1038/s41598-025-88109-x},\n\turl = {https://www.scopus.com/inward/record.uri?eid=2-s2.0-85217357657&doi=10.1038%2Fs41598-025-88109-x&partnerID=40&md5=b3b20522ab87f8bcbd55df0712ce510e},\n\tvolume = {15},\n\tnumber = {1},\n\tnote = {Export Date: 30 March 2026; Cited By: 8 ER -; Article},\n\ttype = {Article},\n\tsource = {Scopus}\n}",
      "source_files": [
        "scopus_export_Mar 30-2026_b9a59ff7-ed41-4872-a208-e0fc4046c226.ris"
      ],
      "source_keys": [
        "10.1038/s41598-025-88109-x"
      ],
      "merged_from": [],
      "status": "unprocessed"
    },
    {
      "paper_id": "paper_000095",
      "entry_type": "article",
      "title": "Cluster Analysis Based Arc Detection in Pantograph-Catenary System",
      "authors": [
        "Huang, S.",
        "Yu, L.",
        "Zhang, F.",
        "Zhu, W.",
        "Guo, Q."
      ],
      "year": 2018,
      "journal": "Journal of Advanced Transportation",
      "doi": "10.1155/2018/1329265",
      "abstract": "The pantograph-catenary system, which ensures the transmission of electrical energy, is a critical component of a high-speed electric multiple unit (EMU) train. The pantograph-catenary arc directly affects the power supply quality. The Chinese Railway High-speed (CRH) is equipped with a 6C system to obtain pantograph videos. However, it is difficult to automatically identify the arc image information from the vast amount of videos. This paper proposes an effective approach with which pantograph video can be separated into continuous frame-by-frame images. Because of the interference from the complex operating environment, it is unreasonable to directly use the arc parameters to detect the arc. An environmental segmentation algorithm is developed to eliminate the interference. Time series in the same environment is analyzed via cluster analysis technique (CAT) to find the abnormal points and simplified arc model to find arc events accurately. The proposed approach is tested with real pantograph video and performs well. © 2018 Shize Huang et al.",
      "keywords": [],
      "normalized_title": "cluster analysis based arc detection in pantograph catenary system",
      "raw_bibtex": "@ARTICLE{10.1155/2018/1329265,\n\tauthor = {Huang, S. and Yu, L. and Zhang, F. and Zhu, W. and Guo, Q.},\n\ttitle = {Cluster Analysis Based Arc Detection in Pantograph-Catenary System},\n\tjournal = {Journal of Advanced Transportation},\n\tyear = {2018},\n\tabstract = {The pantograph-catenary system, which ensures the transmission of electrical energy, is a critical component of a high-speed electric multiple unit (EMU) train. The pantograph-catenary arc directly affects the power supply quality. The Chinese Railway High-speed (CRH) is equipped with a 6C system to obtain pantograph videos. However, it is difficult to automatically identify the arc image information from the vast amount of videos. This paper proposes an effective approach with which pantograph video can be separated into continuous frame-by-frame images. Because of the interference from the complex operating environment, it is unreasonable to directly use the arc parameters to detect the arc. An environmental segmentation algorithm is developed to eliminate the interference. Time series in the same environment is analyzed via cluster analysis technique (CAT) to find the abnormal points and simplified arc model to find arc events accurately. The proposed approach is tested with real pantograph video and performs well. © 2018 Shize Huang et al.},\n\tdoi = {10.1155/2018/1329265},\n\turl = {https://www.scopus.com/inward/record.uri?eid=2-s2.0-85047518132&doi=10.1155%2F2018%2F1329265&partnerID=40&md5=794a34e0f3b298510f35f2284e2f00ed},\n\tvolume = {2018},\n\tnote = {Export Date: 30 March 2026; Cited By: 10 ER -; Article},\n\ttype = {Article},\n\tsource = {Scopus}\n}",
      "source_files": [
        "scopus_export_Mar 30-2026_b9a59ff7-ed41-4872-a208-e0fc4046c226.ris"
      ],
      "source_keys": [
        "10.1155/2018/1329265"
      ],
      "merged_from": [],
      "status": "unprocessed"
    },
    {
      "paper_id": "paper_000096",
      "entry_type": "article",
      "title": "Evolution processes of the tribological properties in pantograph/catenary system affected by dynamic contact force during current-carrying sliding",
      "authors": [
        "Zhang, Y.",
        "Li, C.",
        "Pang, X.",
        "Song, C.",
        "Ni, F.",
        "Zhang, Y."
      ],
      "year": 2021,
      "journal": "Wear",
      "doi": "10.1016/j.wear.2021.203809",
      "abstract": "DSA200 pantograph and CH160 catenary are being in service in China on SS7 electric locomotive. Dynamic study of the pantograph/catenary system found that the contact force between pantograph and contact wire vibrated periodically with the running of trains. Both of the amplitude and frequency of the dynamic contact force increased with the increase of running speeds. In this paper, the effects of dynamic contact force on tribological properties of the pure carbon strip were studied on a homemade pin-on-disk tribometer. A critical point of friction coefficient, wear rate and current-carrying quality at the velocity of 80 km/h was detected subjected to dynamic contact force. Tribological properties of the pure carbon strip deteriorated abruptly when the train ran faster than 80 km/h. Oxidation film on the surface of the strip was produced firstly, and then it grew slowly, at last it was destroyed rapidly with the increase of the running speeds. This transformation leaded to the sudden shift of friction coefficient and wear rate. Meanwhile, the critical point of arcing rate (2%) at 80 km/h was tested. Current-carrying quality of the strip deteriorated abruptly accompanied by the rapidly raised arcing rate. Simultaneously, cracks were generated and extended inner the strip. These cracks destroyed the strip's mechanical property and accelerated the arc erosion. The wear mechanism transferred from mechanical wear to arc erosion with the increase of arcing rate, which were proved to be the most important failure types for pure carbon strip. This study obtained the evolution processes of the tribological properties in pantograph/catenary system, expecting to provide some useful suggestions for the safe operation of locomotives. © 2021 Elsevier B.V.",
      "keywords": [],
      "normalized_title": "evolution processes of the tribological properties in pantograph catenary system affected by dynamic contact force during current carrying sliding",
      "raw_bibtex": "@ARTICLE{10.1016/j.wear.2021.203809,\n\tauthor = {Zhang, Y. and Li, C. and Pang, X. and Song, C. and Ni, F. and Zhang, Y.},\n\ttitle = {Evolution processes of the tribological properties in pantograph/catenary system affected by dynamic contact force during current-carrying sliding},\n\tjournal = {Wear},\n\tyear = {2021},\n\tabstract = {DSA200 pantograph and CH160 catenary are being in service in China on SS7 electric locomotive. Dynamic study of the pantograph/catenary system found that the contact force between pantograph and contact wire vibrated periodically with the running of trains. Both of the amplitude and frequency of the dynamic contact force increased with the increase of running speeds. In this paper, the effects of dynamic contact force on tribological properties of the pure carbon strip were studied on a homemade pin-on-disk tribometer. A critical point of friction coefficient, wear rate and current-carrying quality at the velocity of 80 km/h was detected subjected to dynamic contact force. Tribological properties of the pure carbon strip deteriorated abruptly when the train ran faster than 80 km/h. Oxidation film on the surface of the strip was produced firstly, and then it grew slowly, at last it was destroyed rapidly with the increase of the running speeds. This transformation leaded to the sudden shift of friction coefficient and wear rate. Meanwhile, the critical point of arcing rate (2%) at 80 km/h was tested. Current-carrying quality of the strip deteriorated abruptly accompanied by the rapidly raised arcing rate. Simultaneously, cracks were generated and extended inner the strip. These cracks destroyed the strip's mechanical property and accelerated the arc erosion. The wear mechanism transferred from mechanical wear to arc erosion with the increase of arcing rate, which were proved to be the most important failure types for pure carbon strip. This study obtained the evolution processes of the tribological properties in pantograph/catenary system, expecting to provide some useful suggestions for the safe operation of locomotives. © 2021 Elsevier B.V.},\n\tdoi = {10.1016/j.wear.2021.203809},\n\turl = {https://www.scopus.com/inward/record.uri?eid=2-s2.0-85103136836&doi=10.1016%2Fj.wear.2021.203809&partnerID=40&md5=6007e094088bf753fc6904dec3735af9},\n\tvolume = {477},\n\tnote = {Export Date: 30 March 2026; Cited By: 42 ER -; Article},\n\ttype = {Article},\n\tsource = {Scopus}\n}",
      "source_files": [
        "scopus_export_Mar 30-2026_b9a59ff7-ed41-4872-a208-e0fc4046c226.ris"
      ],
      "source_keys": [
        "10.1016/j.wear.2021.203809"
      ],
      "merged_from": [],
      "status": "unprocessed"
    },
    {
      "paper_id": "paper_000097",
      "entry_type": "article",
      "title": "A pantograph-catenary arcing detection model for high-speed railway based on semantic segmentation and generative adversarial network",
      "authors": [
        "Liu, X.",
        "Wang, X.",
        "Quan, W.",
        "Gu, G.",
        "Xu, X.",
        "Gao, S."
      ],
      "year": 2025,
      "journal": "International Journal of Rail Transportation",
      "doi": "10.1080/23248378.2024.2382117",
      "abstract": "Pantograph-catenary arcing refers to an abnormal phenomenon occurring in pantograph-catenary system due to poor contact or other factors, which significantly impacts the normal operation of high-speed railway. Therefore, the detection of arcing occurrences holds significant importance for the intelligent maintenance of pantograph-catenary systems. However, the scarcity of arcing data in pantograph-catenary datasets limits the efficacy of supervised learning methods for arcing detection. To address this issue, we propose a novel pantograph-catenary arcing detection model that integrates semantic segmentation with generative adversarial networks. The model first modifies the loss function of the U (Formula presented.) -Net network to tailor it specifically for pantograph-catenary semantic segmentation. To generate finer normal pantograph-catenary images, attention mechanism is incorporated into the SPADE-based pantograph-catenary scene generation model. Finally, an improved differencing method is employed to compute the arcing image by subtracting the generated normal pantograph-catenary image from the actual pantograph-catenary image. The experimental results validate the effectiveness of the method for pantograph-catenary arcing detection in the absence of prior arcing knowledge, with a recall rate of 75.3% and an F1-Score of 69.63%. Compared to other advanced pantograph-catenary arcing methods, this method exhibits superior performance. © 2024 Informa UK Limited, trading as Taylor & Francis Group.",
      "keywords": [],
      "normalized_title": "a pantograph catenary arcing detection model for high speed railway based on semantic segmentation and generative adversarial network",
      "raw_bibtex": "@ARTICLE{10.1080/23248378.2024.2382117,\n\tauthor = {Liu, X. and Wang, X. and Quan, W. and Gu, G. and Xu, X. and Gao, S.},\n\ttitle = {A pantograph-catenary arcing detection model for high-speed railway based on semantic segmentation and generative adversarial network},\n\tjournal = {International Journal of Rail Transportation},\n\tyear = {2025},\n\tabstract = {Pantograph-catenary arcing refers to an abnormal phenomenon occurring in pantograph-catenary system due to poor contact or other factors, which significantly impacts the normal operation of high-speed railway. Therefore, the detection of arcing occurrences holds significant importance for the intelligent maintenance of pantograph-catenary systems. However, the scarcity of arcing data in pantograph-catenary datasets limits the efficacy of supervised learning methods for arcing detection. To address this issue, we propose a novel pantograph-catenary arcing detection model that integrates semantic segmentation with generative adversarial networks. The model first modifies the loss function of the U (Formula presented.) -Net network to tailor it specifically for pantograph-catenary semantic segmentation. To generate finer normal pantograph-catenary images, attention mechanism is incorporated into the SPADE-based pantograph-catenary scene generation model. Finally, an improved differencing method is employed to compute the arcing image by subtracting the generated normal pantograph-catenary image from the actual pantograph-catenary image. The experimental results validate the effectiveness of the method for pantograph-catenary arcing detection in the absence of prior arcing knowledge, with a recall rate of 75.3% and an F1-Score of 69.63%. Compared to other advanced pantograph-catenary arcing methods, this method exhibits superior performance. © 2024 Informa UK Limited, trading as Taylor & Francis Group.},\n\tdoi = {10.1080/23248378.2024.2382117},\n\turl = {https://www.scopus.com/inward/record.uri?eid=2-s2.0-85200684509&doi=10.1080%2F23248378.2024.2382117&partnerID=40&md5=0ce42f92d3fcf4338e2e68c2059d773d},\n\tvolume = {13},\n\tnumber = {4},\n\tpages = {773-794},\n\tnote = {Export Date: 30 March 2026; Cited By: 4 ER -; Article},\n\ttype = {Article},\n\tsource = {Scopus}\n}",
      "source_files": [
        "scopus_export_Mar 30-2026_b9a59ff7-ed41-4872-a208-e0fc4046c226.ris"
      ],
      "source_keys": [
        "10.1080/23248378.2024.2382117"
      ],
      "merged_from": [],
      "status": "unprocessed"
    },
    {
      "paper_id": "paper_000098",
      "entry_type": "article",
      "title": "Research on arc length threshold of pantograph-catenary interaction leading to excessive disturbances in traction drive systems",
      "authors": [
        "Chen, J.",
        "Wang, X.",
        "Song, Y."
      ],
      "year": 2026,
      "journal": "Complex Engineering Systems",
      "doi": "10.20517/ces.2025.77",
      "abstract": "With increasing train speeds, intensified vibrations in the pantograph-catenary (PC) system make separation between the pantograph and the contact wire-and the resulting arcing-more likely. These arcs degrade the current collection quality of high-speed trains, destabilize the traction drive system, and generate harmonics and electromagnetic interference that affect onboard communication equipment. This study investigates the impact of PC arcing at different train speeds on the traction system’s input voltage and rectifier-side direct-current (DC) voltage, and determines the corresponding acceptable arc length thresholds. An equivalent impedance model of the autotransformer traction network incorporating messenger wires and droppers is developed, together with a Habedank black-box arc model that accounts for the dynamic variations in dissipated power and voltage gradient with changing arc length. In parallel, an alternating current traction drive system model incorporating a pulse rectifier and traction motor is constructed, and its validity is verified by comparing simulation results with experimental data. Results indicate that within the allowable voltage disturbance range (input voltage 1,085-1,922 V; DC-side fluctuation ≤ 5%), the input voltage arc length threshold decreases from 0.887 cm to 0.826 cm as train speed increases from 200 km/h to 300 km/h, while the DC-side threshold drops from 1.28 cm to 0.75 cm. These findings reveal that higher speeds increase the sensitivity of the traction converter to voltage disturbances-identical arc lengths cause stronger voltage fluctuations. Moreover, for a given train speed, the input voltage arc length threshold remains higher than that of the rectifier-side DC voltage. © The Author(s) 2026. Open Access.",
      "keywords": [],
      "normalized_title": "research on arc length threshold of pantograph catenary interaction leading to excessive disturbances in traction drive systems",
      "raw_bibtex": "@ARTICLE{10.20517/ces.2025.77,\n\tauthor = {Chen, J. and Wang, X. and Song, Y.},\n\ttitle = {Research on arc length threshold of pantograph-catenary interaction leading to excessive disturbances in traction drive systems},\n\tjournal = {Complex Engineering Systems},\n\tyear = {2026},\n\tabstract = {With increasing train speeds, intensified vibrations in the pantograph-catenary (PC) system make separation between the pantograph and the contact wire-and the resulting arcing-more likely. These arcs degrade the current collection quality of high-speed trains, destabilize the traction drive system, and generate harmonics and electromagnetic interference that affect onboard communication equipment. This study investigates the impact of PC arcing at different train speeds on the traction system’s input voltage and rectifier-side direct-current (DC) voltage, and determines the corresponding acceptable arc length thresholds. An equivalent impedance model of the autotransformer traction network incorporating messenger wires and droppers is developed, together with a Habedank black-box arc model that accounts for the dynamic variations in dissipated power and voltage gradient with changing arc length. In parallel, an alternating current traction drive system model incorporating a pulse rectifier and traction motor is constructed, and its validity is verified by comparing simulation results with experimental data. Results indicate that within the allowable voltage disturbance range (input voltage 1,085-1,922 V; DC-side fluctuation ≤ 5%), the input voltage arc length threshold decreases from 0.887 cm to 0.826 cm as train speed increases from 200 km/h to 300 km/h, while the DC-side threshold drops from 1.28 cm to 0.75 cm. These findings reveal that higher speeds increase the sensitivity of the traction converter to voltage disturbances-identical arc lengths cause stronger voltage fluctuations. Moreover, for a given train speed, the input voltage arc length threshold remains higher than that of the rectifier-side DC voltage. © The Author(s) 2026. Open Access.},\n\tdoi = {10.20517/ces.2025.77},\n\turl = {https://www.scopus.com/inward/record.uri?eid=2-s2.0-105029768719&doi=10.20517%2Fces.2025.77&partnerID=40&md5=17890212e407497b8bf4192a127cfd6d},\n\tvolume = {6},\n\tnumber = {1},\n\tnote = {Export Date: 30 March 2026; Cited By: 0 ER -; Article},\n\ttype = {Article},\n\tsource = {Scopus}\n}",
      "source_files": [
        "scopus_export_Mar 30-2026_b9a59ff7-ed41-4872-a208-e0fc4046c226.ris"
      ],
      "source_keys": [
        "10.20517/ces.2025.77"
      ],
      "merged_from": [],
      "status": "unprocessed"
    },
    {
      "paper_id": "paper_000099",
      "entry_type": "article",
      "title": "Experimental research on the mechanism of the delamination extension of the carbon strip with heavy electrical current at the speed of 360 km/h",
      "authors": [
        "Yang, H.",
        "Yang, D.",
        "Mei, G.",
        "Cai, C.",
        "Deng, X.",
        "Yang, Y."
      ],
      "year": 2023,
      "journal": "Wear",
      "doi": "10.1016/j.wear.2023.204718",
      "abstract": "Delamination wear leads to a surge in the wear loss of the carbon strip. It also has a significant influence on the physicochemical properties of the contact pairs in the pantograph-catenary system (over 250 km/h). In this paper, the pure carbon/copper-alloy friction pair was chosen as the research object to study the wear evolution mechanisms and the law of delamination wear extension of the carbon strip, using a ring-on -block wear tester with a design speed of 400 km/h. And the arc discharge energy was calculated to investigate the quantitative relationship between the delamination wear and the arc discharge in the process of the test. The experimental results show that the frictional coefficient increases gradually with the experiment. The frictional coefficient with electric current is much bigger than that without electric current under the same test conditions. Under the intense arcing (when the average single arc discharge energy e > 76J), the delamination wear initially appears on one edge of the strip and gradually extends to the middle of the strip when sliding time t exceeds a certain value, which results in the increase of the wear of the strip and the further enhancement of the arc discharge. The result also indicates that delamination wear and its extension are occurred by the cumulative effect of the heat caused by the long-time strong arc discharge. © 2023 Elsevier B.V.",
      "keywords": [],
      "normalized_title": "experimental research on the mechanism of the delamination extension of the carbon strip with heavy electrical current at the speed of 360 km h",
      "raw_bibtex": "@ARTICLE{10.1016/j.wear.2023.204718,\n\tauthor = {Yang, H. and Yang, D. and Mei, G. and Cai, C. and Deng, X. and Yang, Y.},\n\ttitle = {Experimental research on the mechanism of the delamination extension of the carbon strip with heavy electrical current at the speed of 360 km/h},\n\tjournal = {Wear},\n\tyear = {2023},\n\tabstract = {Delamination wear leads to a surge in the wear loss of the carbon strip. It also has a significant influence on the physicochemical properties of the contact pairs in the pantograph-catenary system (over 250 km/h). In this paper, the pure carbon/copper-alloy friction pair was chosen as the research object to study the wear evolution mechanisms and the law of delamination wear extension of the carbon strip, using a ring-on -block wear tester with a design speed of 400 km/h. And the arc discharge energy was calculated to investigate the quantitative relationship between the delamination wear and the arc discharge in the process of the test. The experimental results show that the frictional coefficient increases gradually with the experiment. The frictional coefficient with electric current is much bigger than that without electric current under the same test conditions. Under the intense arcing (when the average single arc discharge energy e > 76J), the delamination wear initially appears on one edge of the strip and gradually extends to the middle of the strip when sliding time t exceeds a certain value, which results in the increase of the wear of the strip and the further enhancement of the arc discharge. The result also indicates that delamination wear and its extension are occurred by the cumulative effect of the heat caused by the long-time strong arc discharge. © 2023 Elsevier B.V.},\n\tdoi = {10.1016/j.wear.2023.204718},\n\turl = {https://www.scopus.com/inward/record.uri?eid=2-s2.0-85150370301&doi=10.1016%2Fj.wear.2023.204718&partnerID=40&md5=6604e39311230d0eec013f42db6b2acf},\n\tvolume = {522},\n\tnote = {Export Date: 30 March 2026; Cited By: 12 ER -; Article},\n\ttype = {Article},\n\tsource = {Scopus}\n}",
      "source_files": [
        "scopus_export_Mar 30-2026_b9a59ff7-ed41-4872-a208-e0fc4046c226.ris"
      ],
      "source_keys": [
        "10.1016/j.wear.2023.204718"
      ],
      "merged_from": [],
      "status": "unprocessed"
    },
    {
      "paper_id": "paper_000100",
      "entry_type": "article",
      "title": "Experimental Study on the Transient Disturbance Characteristics and Influence Factors of Pantograph–Catenary Discharge",
      "authors": [
        "Jin, M.",
        "Hu, M.",
        "Li, H.",
        "Yang, Y.",
        "Liu, W.",
        "Fang, Q.",
        "Liu, S."
      ],
      "year": 2022,
      "journal": "Energies",
      "doi": "10.3390/en15165959",
      "abstract": "The transient electromagnetic disturbance generated by arcing discharge between the pantograph and catenary can pose a significant risk to the safe operation of electrified railways. In order to better comprehend its properties, a pantograph–catenary discharge generating device is designed to simulate the discharge phenomenon with moving electrodes in this experimental investigation. The effects of the applied voltage, the gap distance, and the relative motion between the pantograph and catenary on the time- and frequency-domain features of the discharge current and electromagnetic field are investigated. The variation trends of pulse peak current, rise time, pulse repetition frequency, maximum amplitude, and characteristic frequency in the radiation spectrum are retrieved under varying experimental settings, and the effect mechanisms are derived from the physics of gas discharge. A dynamic discharge test is conducted in this study in order to further understand the effect of electrodes’ relative motion on discharge characteristics. The results indicate that lateral sliding motion of the pantograph along the track has a negligible effect on the transient discharge, whereas a faster vertical approaching motion between the pantograph and catenary generates a larger pulse current peak, a steeper rise front-edge, and a higher radiation intensity. © 2022 by the authors.",
      "keywords": [],
      "normalized_title": "experimental study on the transient disturbance characteristics and influence factors of pantograph catenary discharge",
      "raw_bibtex": "@ARTICLE{10.3390/en15165959,\n\tauthor = {Jin, M. and Hu, M. and Li, H. and Yang, Y. and Liu, W. and Fang, Q. and Liu, S.},\n\ttitle = {Experimental Study on the Transient Disturbance Characteristics and Influence Factors of Pantograph–Catenary Discharge},\n\tjournal = {Energies},\n\tyear = {2022},\n\tabstract = {The transient electromagnetic disturbance generated by arcing discharge between the pantograph and catenary can pose a significant risk to the safe operation of electrified railways. In order to better comprehend its properties, a pantograph–catenary discharge generating device is designed to simulate the discharge phenomenon with moving electrodes in this experimental investigation. The effects of the applied voltage, the gap distance, and the relative motion between the pantograph and catenary on the time- and frequency-domain features of the discharge current and electromagnetic field are investigated. The variation trends of pulse peak current, rise time, pulse repetition frequency, maximum amplitude, and characteristic frequency in the radiation spectrum are retrieved under varying experimental settings, and the effect mechanisms are derived from the physics of gas discharge. A dynamic discharge test is conducted in this study in order to further understand the effect of electrodes’ relative motion on discharge characteristics. The results indicate that lateral sliding motion of the pantograph along the track has a negligible effect on the transient discharge, whereas a faster vertical approaching motion between the pantograph and catenary generates a larger pulse current peak, a steeper rise front-edge, and a higher radiation intensity. © 2022 by the authors.},\n\tdoi = {10.3390/en15165959},\n\turl = {https://www.scopus.com/inward/record.uri?eid=2-s2.0-85137710865&doi=10.3390%2Fen15165959&partnerID=40&md5=2cfaf3238520629c4199bd04d167b587},\n\tvolume = {15},\n\tnumber = {16},\n\tnote = {Export Date: 30 March 2026; Cited By: 11 ER -; Article},\n\ttype = {Article},\n\tsource = {Scopus}\n}",
      "source_files": [
        "scopus_export_Mar 30-2026_b9a59ff7-ed41-4872-a208-e0fc4046c226.ris"
      ],
      "source_keys": [
        "10.3390/en15165959"
      ],
      "merged_from": [],
      "status": "unprocessed"
    }
  ]
}
