{
  "batch_id": "batch_0006",
  "paper_count": 1,
  "paper_ids": [
    "paper_000051"
  ],
  "papers": [
    {
      "paper_id": "paper_000051",
      "entry_type": "article",
      "title": "“互联网+”延续护理在老年慢性病患者的应用",
      "authors": [
        "张樱婷",
        "于淑梅",
        "宋绍征"
      ],
      "year": 2021,
      "journal": "科学咨询(科技·管理)",
      "doi": null,
      "abstract": "本文通过检索近年来\"互联网+\"延续护理在老年慢性病患者应用的相关文献,对\"互联网+\"延续护理概念、发展背景、特点及应用形式进行综述,文中涉及的应用形式包括常规通信软件、移动健康应用程序APP、网络平台、医院-社区-家庭三元联动的患者管理网络、人工智能技术,对比国内外\"互联网+\"延续护理应用的现状,总结在应用中所存在的问题,从患者、医护、\"互联网+\"技术角度分析,给出相应对策,为未来推广\"互联网+\"延续护理模式在护理老年慢性病患者应用提出展望。",
      "keywords": [
        "“互联网+”",
        "延续护理",
        "健康",
        "老年慢性病"
      ],
      "normalized_title": "互联网 延续护理在老年慢性病患者的应用",
      "raw_bibtex": "@ARTICLE{endnote_000051,\n\tauthor = {张樱婷 and 于淑梅 and 宋绍征},\n\ttitle = {“互联网+”延续护理在老年慢性病患者的应用},\n\tjournal = {科学咨询(科技·管理)},\n\tyear = {2021},\n\tkeywords = {“互联网+”;延续护理;健康;老年慢性病},\n\tabstract = {本文通过检索近年来\"互联网+\"延续护理在老年慢性病患者应用的相关文献,对\"互联网+\"延续护理概念、发展背景、特点及应用形式进行综述,文中涉及的应用形式包括常规通信软件、移动健康应用程序APP、网络平台、医院-社区-家庭三元联动的患者管理网络、人工智能技术,对比国内外\"互联网+\"延续护理应用的现状,总结在应用中所存在的问题,从患者、医护、\"互联网+\"技术角度分析,给出相应对策,为未来推广\"互联网+\"延续护理模式在护理老年慢性病患者应用提出展望。},\n\turl = {https://kns.cnki.net/kcms2/article/abstract?v=Vs3rztogjcVaESV0RwakgfKqp_3hH_YjkCS-3fJdCCeBSfDRQ74Z--ZqbpFUyn2pwKFytld-wgzEJvADLu6IEHmVxt1plYjyYSggtGaOOTCjJkRF1tcCiQc8J7W8-6jMBzqEEfcEHGdboti-58dpfN6epu0z6pSnuiyNE7fDFjvGdzpM4X8ueYK9NgJnfA7a&uniplatform=NZKPT&language=CHS},\n\tnumber = {10},\n\tpages = {53-55},\n\tissn = {1671-4822},\n\tnote = {CNKI}\n}",
      "source_files": [
        "CNKI-20260403235449690.enw"
      ],
      "source_keys": [
        "endnote_000051"
      ],
      "merged_from": [],
      "status": "unprocessed"
    }
  ]
}
