{
  "batch_id": "batch_0020",
  "results": [
    {
      "paper_id": "paper_000191",
      "decision": "exclude",
      "reason": "标题和摘要仅涉及胃肠道肿瘤术后影像诊断，未提及辐射暴露或肠道健康影响。",
      "evidence": [
        "title",
        "abstract"
      ],
      "confidence": 0.95
    },
    {
      "paper_id": "paper_000192",
      "decision": "exclude",
      "reason": "标题和摘要研究成人肠套叠的影像预测因子和治疗策略，未涉及辐射暴露或肠道健康影响。",
      "evidence": [
        "title",
        "abstract"
      ],
      "confidence": 0.95
    },
    {
      "paper_id": "paper_000193",
      "decision": "exclude",
      "reason": "标题和摘要比较CT与透视检测胃肠道术后泄漏，未提及辐射暴露或肠道健康影响。",
      "evidence": [
        "title",
        "abstract"
      ],
      "confidence": 0.95
    },
    {
      "paper_id": "paper_000194",
      "decision": "exclude",
      "reason": "标题和摘要比较造影剂在CT结肠成像中的性能，未涉及辐射暴露或肠道健康影响。",
      "evidence": [
        "title",
        "abstract"
      ],
      "confidence": 0.95
    },
    {
      "paper_id": "paper_000195",
      "decision": "exclude",
      "reason": "标题和摘要评估急诊影像检查的适当性，未提及辐射暴露或肠道健康影响。",
      "evidence": [
        "title",
        "abstract"
      ],
      "confidence": 0.95
    },
    {
      "paper_id": "paper_000196",
      "decision": "exclude",
      "reason": "标题和摘要讨论异物影像表现，未涉及辐射暴露或肠道健康影响。",
      "evidence": [
        "title",
        "abstract"
      ],
      "confidence": 0.95
    },
    {
      "paper_id": "paper_000197",
      "decision": "exclude",
      "reason": "标题和摘要提供胆囊息肉管理共识，未提及辐射暴露或肠道健康影响。",
      "evidence": [
        "title",
        "abstract"
      ],
      "confidence": 0.95
    },
    {
      "paper_id": "paper_000198",
      "decision": "exclude",
      "reason": "标题和摘要描述胰腺癌患者Lemierre综合征腹部变异，未涉及辐射暴露或肠道健康影响。",
      "evidence": [
        "title",
        "abstract"
      ],
      "confidence": 0.95
    },
    {
      "paper_id": "paper_000199",
      "decision": "exclude",
      "reason": "标题和摘要讨论黑色素瘤小肠转移影像表现，未提及辐射暴露或肠道健康影响。",
      "evidence": [
        "title",
        "abstract"
      ],
      "confidence": 0.95
    },
    {
      "paper_id": "paper_000200",
      "decision": "exclude",
      "reason": "标题和摘要研究胃肠道间质瘤影像组学预测伊马替尼反应，未涉及辐射暴露或肠道健康影响。",
      "evidence": [
        "title",
        "abstract"
      ],
      "confidence": 0.95
    }
  ]
}
